{"_invocation_id": "a68f4521-1d09-4030-a579-64b16d44aa50", "linked": {"0": {"name": "source.sakila_dbt.stg.cust", "type": "source", "succ": [22]}, "1": {"name": "source.sakila_dbt.stg.address", "type": "source", "succ": [23]}, "2": {"name": "source.sakila_dbt.stg.city", "type": "source", "succ": [23]}, "3": {"name": "source.sakila_dbt.stg.staff", "type": "source", "succ": [25]}, "4": {"name": "source.sakila_dbt.stg.store", "type": "source", "succ": [24]}, "5": {"name": "source.sakila_dbt.stg.z_refresh_from", "type": "source", "succ": [37]}, "6": {"name": "source.sakila_dbt.stg.payment", "type": "source", "succ": [26]}, "7": {"name": "source.sakila_dbt.stg.rental", "type": "source", "succ": [37]}, "8": {"name": "source.sakila_dbt.stg.country", "type": "source", "succ": [23]}, "9": {"name": "source.sakila_dbt.stg.film", "type": "source", "succ": [27]}, "10": {"name": "source.sakila_dbt.stg.film_category", "type": "source", "succ": [27]}, "11": {"name": "source.sakila_dbt.stg.category", "type": "source", "succ": [27]}, "12": {"name": "source.sakila_dbt.stg.language", "type": "source", "succ": [27]}, "13": {"name": "source.sakila_dbt.stg.inventory", "type": "source", "succ": [37]}, "14": {"name": "model.sakila_dbt.dim_date", "type": "model", "succ": [20, 21]}, "15": {"name": "seed.sakila_dbt.country", "type": "seed"}, "16": {"name": "operation.sakila_dbt.sakila_dbt-on-run-start-0", "type": "operation"}, "17": {"name": "operation.sakila_dbt.sakila_dbt-on-run-start-1", "type": "operation"}, "18": {"name": "operation.sakila_dbt.sakila_dbt-on-run-start-2", "type": "operation"}, "19": {"name": "operation.sakila_dbt.sakila_dbt-on-run-end-0", "type": "operation"}, "20": {"name": "test.sakila_dbt.unique_dim_date_date_dim_id.8ef810b6d3", "type": "test"}, "21": {"name": "test.sakila_dbt.not_null_dim_date_date_dim_id.b5878fcef1", "type": "test"}, "22": {"name": "model.sakila_dbt.dim_customer", "type": "model", "succ": [28, 37]}, "23": {"name": "model.sakila_dbt.location_data", "type": "model", "succ": [22, 24]}, "24": {"name": "model.sakila_dbt.dim_store", "type": "model", "succ": [29, 30, 37]}, "25": {"name": "model.sakila_dbt.dim_staff", "type": "model", "succ": [24, 31, 32, 37]}, "26": {"name": "model.sakila_dbt.fact_payment", "type": "model", "succ": [35, 36]}, "27": {"name": "model.sakila_dbt.dim_film", "type": "model", "succ": [33, 34, 37]}, "28": {"name": "test.sakila_dbt.accepted_values_dim_customer_is_active__yes__no.b917e2d6c9", "type": "test"}, "29": {"name": "test.sakila_dbt.unique_dim_store_store_id.90e408e197", "type": "test"}, "30": {"name": "test.sakila_dbt.not_null_dim_store_store_id.8cb7c6ace0", "type": "test"}, "31": {"name": "test.sakila_dbt.unique_dim_staff_staff_id.25db3cb97c", "type": "test"}, "32": {"name": "test.sakila_dbt.not_null_dim_staff_staff_id.a7e1517ac1", "type": "test"}, "33": {"name": "test.sakila_dbt.unique_dim_film_film_id.61e8921339", "type": "test"}, "34": {"name": "test.sakila_dbt.not_null_dim_film_film_id.004a583c6e", "type": "test"}, "35": {"name": "test.sakila_dbt.unique_fact_payment_payment_id.22e3c4b51b", "type": "test"}, "36": {"name": "test.sakila_dbt.not_null_fact_payment_payment_id.335388b645", "type": "test"}, "37": {"name": "model.sakila_dbt.fact_rental", "type": "model", "succ": [38, 39]}, "38": {"name": "test.sakila_dbt.unique_fact_rental_rental_id.e588282db6", "type": "test"}, "39": {"name": "test.sakila_dbt.not_null_fact_rental_rental_id.54be912a16", "type": "test"}}}